lilist.py
setup.py
lilist.egg-info/PKG-INFO
lilist.egg-info/SOURCES.txt
lilist.egg-info/dependency_links.txt
lilist.egg-info/top_level.txt