Metadata-Version: 1.0
Name: lilist
Version: 0.1.0
Summary: A linear interpolation list class
Home-page: http://github.com/MatthewScholefield/lilist
Author: Matthew Scholefield
Author-email: matthew331199@gmail.com
License: MIT
Platform: UNKNOWN
